[
  {"order_id": 6363763262239, "customer_id": 465, "products": [{"prod_id": "abc12345", "name": "Asus Laptop", "price": 429.99},
                                                               {"prod_id": "def45678","name": "Karcher Hose Set","price": 23.43}]},
  {"order_id": 1197372932325, "customer_id": 10408, "products": [{"prod_id": "abc12345", "name": "Asus Laptop", "price": 429.99}]},
  {"order_id": 9812343774839, "customer_id": 503, "products": [{"prod_id": "pqr88223", "name": "Morphy Richardds Food Mixer", "price": 431.43},
                                                               {"prod_id": "def45678","name": "Karcher Hose Set","price": 23.43}]},
  {"order_id": 4433997244387, "customer_id": 415981, "products": [{"prod_id": "def45678", "name": "Karcher Hose Set", "price": 23.43},
                                                                  {"prod_id": "jkl77336","name": "Picky Pencil Sharpener","price": 0.67},
                                                                  {"prod_id": "xyz11228","name": "Russell Hobbs Chrome Kettle","price": 15.76}]}
]